graphite_api/__init__.py
graphite_api/app.py
graphite_api/carbonlink.py
graphite_api/config.py
graphite_api/encoders.py
graphite_api/evaluator.py
graphite_api/functions.py
graphite_api/intervals.py
graphite_api/middleware.py
graphite_api/node.py
graphite_api/readers.py
graphite_api/storage.py
graphite_api/utils.py
graphite_api/_vendor/__init__.py
graphite_api/_vendor/whisper.py
graphite_api/finders/__init__.py
graphite_api/finders/whisper.py
graphite_api/render/__init__.py
graphite_api/render/attime.py
graphite_api/render/datalib.py
graphite_api/render/glyph.py
graphite_api/render/grammar.py
influxgraph_graphite_api/__init__.py
influxgraph_graphite_api/_version.py
influxgraph_graphite_api/app.py
influxgraph_graphite_api/carbonlink.py
influxgraph_graphite_api/config.py
influxgraph_graphite_api/encoders.py
influxgraph_graphite_api/evaluator.py
influxgraph_graphite_api/functions.py
influxgraph_graphite_api/intervals.py
influxgraph_graphite_api/middleware.py
influxgraph_graphite_api/node.py
influxgraph_graphite_api/readers.py
influxgraph_graphite_api/storage.py
influxgraph_graphite_api/utils.py
influxgraph_graphite_api/_vendor/__init__.py
influxgraph_graphite_api/_vendor/whisper.py
influxgraph_graphite_api/finders/__init__.py
influxgraph_graphite_api/finders/whisper.py
influxgraph_graphite_api/render/__init__.py
influxgraph_graphite_api/render/attime.py
influxgraph_graphite_api/render/datalib.py
influxgraph_graphite_api/render/glyph.py
influxgraph_graphite_api/render/grammar.py
influxgraph_graphite_api-1.2.0.dist-info/DESCRIPTION.rst
influxgraph_graphite_api-1.2.0.dist-info/METADATA
influxgraph_graphite_api-1.2.0.dist-info/RECORD
influxgraph_graphite_api-1.2.0.dist-info/WHEEL
influxgraph_graphite_api-1.2.0.dist-info/metadata.json
influxgraph_graphite_api-1.2.0.dist-info/top_level.txt
